LICENSE
MANIFEST.in
README.markdown
setup.py
django_s3_collectstatic/__init__.py
django_s3_collectstatic.egg-info/PKG-INFO
django_s3_collectstatic.egg-info/SOURCES.txt
django_s3_collectstatic.egg-info/dependency_links.txt
django_s3_collectstatic.egg-info/top_level.txt
django_s3_collectstatic/management/__init__.py
django_s3_collectstatic/management/commands/__init__.py
django_s3_collectstatic/management/commands/fasts3collectstatic.py