Metadata-Version: 1.1
Name: django-s3-collectstatic
Version: 1.0
Summary: UNKNOWN
Home-page: https://github.com/agoodid/django-s3-collectstatic
Author: AGoodId
Author-email: teknik@agoodid.com
License: MIT
Platform: UNKNOWN
Classifier: Development Status :: 5 - Production/Stable
Classifier: Framework :: Django
Classifier: Intended Audience :: Developers
Classifier: License :: OSI Approved :: MIT License
